MANIFEST.in
README.rst
requirements.txt
setup.cfg
setup.py
gmd/__init__.py
gmd/_version.py
gmd/gmd.py
gmd/libgmdc.pyx
gmd.egg-info/PKG-INFO
gmd.egg-info/SOURCES.txt
gmd.egg-info/dependency_links.txt
gmd.egg-info/not-zip-safe
gmd.egg-info/requires.txt
gmd.egg-info/top_level.txt
gmd/tests/__init__.py
gmd/tests/test_common.py
gmd/tests/test_compare_with_R.py
gmd/tests/test_gmd.py
gmd/tests/res/deviations_compare_with_R.csv
gmd/tests/res/dt_uniform.csv
gmd/tests/res/slice_from_r_0.71789.csv