Metadata-Version: 2.1
Name: gmd
Version: 0.0.1
Summary: A scikit-learn compatible python/cython implementation of the GMD algorithm.
Home-page: https://github.com/FlopsKa/gmd
Maintainer: Florian Kalinke
Maintainer-email: flops.ka@gmail.com
License: MIT
Download-URL: https://github.com/FlopsKa/gmd
Platform: UNKNOWN
Classifier: Intended Audience :: Science/Research
Classifier: Intended Audience :: Developers
Classifier: License :: OSI Approved
Classifier: Programming Language :: Python
Classifier: Topic :: Software Development
Classifier: Topic :: Scientific/Engineering
Classifier: Topic :: Software Development :: Libraries :: Python Modules
Classifier: Operating System :: Unix
Classifier: Programming Language :: Python :: 3.7
Provides-Extra: docs
Provides-Extra: tests
